{"artefact": "golang-project-distribution-exported-api", "product": "Fedora", "build": "golang-github-google-go-querystring-0-0.5.git547ef5a.fc24", "commit": "547ef5ac979778feb2f760cdb5f4eae1a2207b86", "distribution": "rawhide", "packages": [{"data": [{"variables": [], "datatypes": [{"name": "Encoder", "def": {"type": "interface", "methods": [{"name": "EncodeValues", "def": {"params": [{"type": "identifier", "def": "string"}, {"type": "pointer", "def": {"item": "Values", "prefix": {"type": "identifier", "def": "url"}, "type": "selector"}}], "type": "function", "results": [{"type": "identifier", "def": "error"}]}}]}}], "functions": [{"name": "Values", "def": {"params": [{"type": "interface", "methods": []}], "type": "function", "results": [{"item": "Values", "prefix": {"type": "identifier", "def": "url"}, "type": "selector"}, {"type": "identifier", "def": "error"}]}}, {"name": "Contains", "def": {"type": "method", "def": {"params": [{"type": "identifier", "def": "string"}], "type": "function", "results": [{"type": "identifier", "def": "bool"}]}, "receiver": {"type": "identifier", "def": "tagOptions"}}}], "package": "github.com/google/go-querystring/query"}], "ipprefix": "github.com/google/go-querystring"}], "rpm": "golang-github-google-go-querystring-devel-0-0.5.git547ef5a.fc24.noarch.rpm"}