{"artefact": "golang-project-distribution-packages", "rpm": "golang-github-eapache-go-resiliency-devel-0-0.4.gitb86b1ec.fc26.noarch.rpm", "product": "Fedora", "build": "golang-github-eapache-go-resiliency-0-0.4.gitb86b1ec.fc26", "commit": "b86b1ec0dd4209a588dc1285cdd471e73525c0b3", "distribution": "rawhide", "data": [{"main": [], "tests": [], "packages": ["github.com/eapache/go-resiliency/semaphore", "github.com/eapache/go-resiliency/retrier", "github.com/eapache/go-resiliency/deadline", "github.com/eapache/go-resiliency/batcher", "github.com/eapache/go-resiliency/breaker"], "dependencies": [{"dependencies": [{"name": "errors", "location": ["semaphore.go"]}, {"name": "time", "location": ["semaphore.go"]}], "qualifier": "semaphore", "package": "github.com/eapache/go-resiliency/semaphore"}, {"dependencies": [{"name": "math/rand", "location": ["retrier.go"]}, {"name": "time", "location": ["backoffs.go", "retrier.go"]}], "qualifier": "retrier", "package": "github.com/eapache/go-resiliency/retrier"}, {"dependencies": [{"name": "errors", "location": ["deadline.go"]}, {"name": "time", "location": ["deadline.go"]}], "qualifier": "deadline", "package": "github.com/eapache/go-resiliency/deadline"}, {"dependencies": [{"name": "sync", "location": ["batcher.go"]}, {"name": "time", "location": ["batcher.go"]}], "qualifier": "batcher", "package": "github.com/eapache/go-resiliency/batcher"}, {"dependencies": [{"name": "errors", "location": ["breaker.go"]}, {"name": "sync", "location": ["breaker.go"]}, {"name": "sync/atomic", "location": ["breaker.go"]}, {"name": "time", "location": ["breaker.go"]}], "qualifier": "breaker", "package": "github.com/eapache/go-resiliency/breaker"}], "ipprefix": "github.com/eapache/go-resiliency"}]}